flask_rapid/__init__.py
flask_rapid-0.0.0.dist-info/LICENSE
flask_rapid-0.0.0.dist-info/METADATA
flask_rapid-0.0.0.dist-info/WHEEL
flask_rapid-0.0.0.dist-info/top_level.txt
flask_rapid-0.0.0.dist-info/RECORD
